tsb_kit/__init__.py
tsb_kit/models/AE.py
tsb_kit/models/__init__.py
tsb_kit/models/cnn.py
tsb_kit/models/damp.py
tsb_kit/models/detectorA.py
tsb_kit/models/detectorB.py
tsb_kit/models/distance.py
tsb_kit/models/feature.py
tsb_kit/models/hbos.py
tsb_kit/models/iforest.py
tsb_kit/models/lof.py
tsb_kit/models/lstm.py
tsb_kit/models/matrix_profile.py
tsb_kit/models/ocsvm.py
tsb_kit/models/pca.py
tsb_kit/models/poly.py
tsb_kit/models/sand.py
tsb_kit/models/sklearn_base.py
tsb_kit/utils/__init__.py
tsb_kit/utils/slidingWindows.py
tsb_kit/utils/stat_models.py
tsb_kit/utils/utility.py
tsb_kit/utils/visualisation.py
tsb_kit/vus/__init__.py
tsb_kit/vus/basic_metrics.py
tsb_kit/vus/metrics.py
tsb_kit/vus/affiliation/__init__.py
tsb_kit/vus/affiliation/_affiliation_zone.py
tsb_kit/vus/affiliation/_integral_interval.py
tsb_kit/vus/affiliation/_single_ground_truth_event.py
tsb_kit/vus/affiliation/generics.py
tsb_kit/vus/affiliation/metrics.py
tsb_kit/vus/utils/__init__.py
tsb_kit/vus/utils/metrics.py
tsb_kit-1.0.1.dist-info/LICENSE
tsb_kit-1.0.1.dist-info/METADATA
tsb_kit-1.0.1.dist-info/WHEEL
tsb_kit-1.0.1.dist-info/top_level.txt
tsb_kit-1.0.1.dist-info/zip-safe
tsb_kit-1.0.1.dist-info/RECORD
